[
    {
      "title": "ปืนในภาพมาจากประเทศอะไร",
      "options": [
        "ไทย",
        "พม่า",
        "ออสเตเลีย",
        "เยอรมนี",
        "ออสเตรีย"
      ],
      "answer": 5,
      "image": "images/Glock17Gen5.webp"
    },
    {
        "title": "ปืนในภาพมาจากประเทศอะไร",
        "options": [
          "ไทย",
          "เกาหลี",
          "ออสเตเลีย",
          "เยอรมนี",
          "ออสเตรีย"
        ],
      "answer": 4,
      "image": "images/Heckler_&_Koch_MP5-1.jpg"
    },
    {
        "title": "ปืนในภาพชื่อว่าอะไร",
        "options": [
          "MP5",
          "SR16",
          "MP7",
          "M110A1",
          "HK USP 9mm"
        ],
        "answer": 2,
        "image": "images/Sr16.webp"
      },
      {
        "title": "ปืนในภาพชื่อว่าอะไร",
        "options": [
          "MP5",
          "SR16",
          "MP7",
          "M110A1",
          "HK USP 9mm"
        ],
        "answer": 3,
        "image": "images/MP7.webp"
      },
      {
        "title": "ปืนในภาพชื่อว่าอะไร",
        "options": [
          "MP5",
          "SR16",
          "MP7",
          "M110A1",
          "H&K USP 9mm"
        ],
        "answer": 5,
        "image": "images/First-year_H&K_USP_9mm.png"
      },
      {
        "title": "ปืนในภาพชื่อว่าอะไร",
        "options": [
          "MP5",
          "SR16",
          "MP7",
          "M110A1",
          "H&K USP 9mm"
        ],
        "answer": 4,
        "image": "images/m110a1.webp"
      },
      {
        "title": "ปืนในภาพชื่อว่าอะไร",
        "options": [
          "SIG MPX",
          "COLT M5",
          "AAC HONEY BADGER",
          "MP7",
          "AUG A3"
        ],
        "answer": 5,
        "image": "images/AUG-A3.jpg"
      },
      {
        "title": "ปืนในภาพชื่อว่าอะไร",
        "options": [
          "SIG MPX",
          "COLT M5",
          "AAC HONEY BADGER",
          "MP7",
          "AUG A3"
        ],
        "answer": 1,
        "image": "images/Sig-MPX.webp"
      },
      {
        "title": "ปืนในภาพชื่อว่าอะไร",
        "options": [
          "SIG MPX",
          "COLT M5",
          "AAC HONEY BADGER",
          "MP7",
          "AUG A3"
        ],
        "answer": 2,
        "image": "images/colt_M5.jpg"
      },
      {
        "title": "ปืนในภาพชื่อว่าอะไร",
        "options": [
          "SIG MPX",
          "COLT M5",
          "AAC HONEY BADGER",
          "MP7",
          "AUG A3"
        ],
        "answer": 3,
        "image": "images/AAC honey badger.jpg"
      },
      {
        "title": "ปืนในภาพชื่อว่าอะไร",
        "options": [
          "SIG MPX",
          "COLT M5",
          "AAC HONEY BADGER",
          "MP7",
          "AUG A3"
        ],
        "answer": 4,
        "image": "images/MP7_.webp"
      },
      {
        "title": "ปืนในภาพชื่อว่าอะไร",
        "options": [
          "H&K VP9",
          "S&W M&P9 M2.0",
          "CMMG BANSHEE",
          "CZ SHADOW 2",
          "KRISS VECTOR SDP"
        ],
        "answer": 1,
        "image": "images/HK_VP9.jpg"
      },
      {
        "title": "ปืนในภาพชื่อว่าอะไร",
        "options": [
          "H&K VP9",
          "S&W M&P9 M2.0",
          "CMMG BANSHEE",
          "CZ SHADOW 2",
          "KRISS VECTOR SDP"
        ],
        "answer": 2,
        "image": "images/S&W M&P9 M2.0.jpg"
      },
      {
        "title": "ปืนในภาพชื่อว่าอะไร",
        "options": [
          "H&K VP9",
          "S&W M&P9 M2.0",
          "CMMG BANSHEE",
          "CZ SHADOW 2",
          "KRISS VECTOR SDP"
        ],
        "answer": 3,
        "image": "images/cmmg_banshee.png"
      },
      {
        "title": "ปืนในภาพชื่อว่าอะไร",
        "options": [
          "H&K VP9",
          "S&W M&P9 M2.0",
          "CMMG BANSHEE",
          "CZ SHADOW 2",
          "KRISS VECTOR SDP"
        ],
        "answer": 4,
        "image": "images/CZ SHADOW 2.png"
      },
      {
        "title": "ปืนในภาพชื่อว่าอะไร",
        "options": [
          "H&K VP9",
          "S&W M&P9 M2.0",
          "CMMG BANSHEE",
          "CZ SHADOW 2",
          "KRISS VECTOR SDP"
        ],
        "answer": 5,
        "image": "images/kriss-vector-1.jpg"
      },
      {
        "title": "ปืนในภาพชื่อว่าอะไร",
        "options": [
          "BUL ARMORY 2011 SAS",
          "BENELLI M2",
          "BENELLI M1014",
          "BARRETTA M82A1",
          "BERETTA 92FS"
        ],
        "answer": 2,
        "image": "images/benelli m2.jpg"
      },
      {
        "title": "ปืนในภาพชื่อว่าอะไร",
        "options": [
          "BUL ARMORY 2011 SAS",
          "BENELLI M2",
          "BENELLI M1014",
          "BARRETTA M82A1",
          "BERETTA 92FS"
        ],
        "answer": 3,
        "image": "images/benelli-m1014.avif"
      },
      {
        "title": "ปืนในภาพชื่อว่าอะไร",
        "options": [
          "BUL ARMORY 2011 SAS",
          "BENELLI M2",
          "BENELLI M1014",
          "BARRETTA M82A1",
          "BERETTA 92FS"
        ],
        "answer": 4,
        "image": "images/Barrett-M82A1.jpg"
      },
      {
        "title": "ปืนในภาพชื่อว่าอะไร",
        "options": [
          "BUL ARMORY 2011 SAS",
          "BENELLI M2",
          "BENELLI M1014",
          "BARRETTA M82A1",
          "BERETTA 92FS"
        ],
        "answer": 5,
        "image": "images/BERETTA 92FS.jpg"
      }
  ]
  